satflow/__init__.py
satflow/run.py
satflow/version.py
satflow/data/__init__.py
satflow/data/datamodules.py
satflow/data/datasets.py
satflow/models/__init__.py
satflow/models/attention_unet.py
satflow/models/cloudgan.py
satflow/models/conv_lstm.py
satflow/models/deeplabv3.py
satflow/models/fcn.py
satflow/models/perceiver.py
satflow/models/perceiverio.py
satflow/models/pix2pix.py
satflow/models/pixel_cnn.py
satflow/models/pl_metnet.py
satflow/models/runet.py
satflow/models/unet.py
satflow/models/utils.py
satflow-0.3.36.dist-info/LICENSE
satflow-0.3.36.dist-info/METADATA
satflow-0.3.36.dist-info/WHEEL
satflow-0.3.36.dist-info/top_level.txt
satflow-0.3.36.dist-info/RECORD
