Metadata-Version: 2.1
Name: satflow
Version: 0.3.36
Summary: Satellite Optical Flow
Home-page: https://github.com/openclimatefix/satflow
Author: Jacob Bieker
Author-email: jacob@openclimatefix.org
License: MIT License
Classifier: Development Status :: 4 - Beta
Classifier: Intended Audience :: Developers
Classifier: Topic :: Scientific/Engineering :: Artificial Intelligence
Classifier: License :: OSI Approved :: MIT License
Classifier: Programming Language :: Python :: 3.8
License-File: LICENSE
Requires-Dist: albumentations (>=1.0.3)
Requires-Dist: antialiased-cnns (>=0.3)
Requires-Dist: hydra-core (>=1.1.0)
Requires-Dist: hydra-optuna-sweeper (>=1.1.0)
Requires-Dist: hydra-colorlog
Requires-Dist: lightning-bolts (>=0.3.4)
Requires-Dist: neptune-client (>=0.10.2)
Requires-Dist: neptune-pytorch-lightning (>=0.9.7)
Requires-Dist: pytest (>=6.2.4)
Requires-Dist: python-dotenv (>=0.19.0)
Requires-Dist: pytorch-msssim (>=0.2.1)
Requires-Dist: rich (>=10.6.0)
Requires-Dist: torchvision (>=0.10.0)
Requires-Dist: affine (==2.3.0)
Requires-Dist: torch-optimizer
Requires-Dist: huggingface-hub (>=0.0.16)
Requires-Dist: einops (>=0.3.2)
Requires-Dist: metnet (>=0.0.3)
Requires-Dist: skillful-nowcasting (>=0.0.2)
Requires-Dist: perceiver-model (>=0.7.0)
Requires-Dist: nowcasting-dataset (>=1.0.21)
Requires-Dist: nowcasting-utils (>=0.0.8)
Requires-Dist: transformers
Requires-Dist: torch
